{
  "GeocodedResearchRelease": [
    {
      "SomaliaDAD": [
        {
          "donors": 100, 
          "runs": 1, 
          "total_projects": 1217, 
          "end_year": "2014", 
          "geocoded_commitments": 2249335593, 
          "geocoded_projects": 1208, 
          "start_year": "2000", 
          "last_run": "2015-11-10T12:31:56.675022", 
          "locations": 3121, 
          "geocoded_disbursements": 1446836907, 
          "total_disbursements": 1488733795, 
          "total_commitments": 2303515442, 
          "scores": [
            {
              "date_coverage": 100.0, 
              "geographic_coverage": 99.26, 
              "geographic_precision": 32.81, 
              "compare_financials": 36.35, 
              "sector_detail": 98.03
            }
          ]
        }
      ]
    }
  ]
}